sphinx_metavar.py
sphinx_metavar-0.1.3.dist-info/WHEEL
sphinx_metavar-0.1.3.dist-info/METADATA
sphinx_metavar-0.1.3.dist-info/RECORD
