Metadata-Version: 2.1
Name: sphinx_metavar
Version: 0.1.3
Summary: Sphinx extension adding semantic markup for metasyntactic variables.
Author-email: Jean Abou-Samra <jean@abou-samra.fr>
Classifier: Framework :: Sphinx :: Extension
Classifier: License :: OSI Approved :: The Unlicense (Unlicense)
Project-URL: Documentation, https://sphinx-metavar.readthedocs.io
Project-URL: Home, https://gitlab.com/jeanas/sphinx-metavar
